{
    "IAMUsers": [
        {
            "User": {
                "Arn": "arn:aws:iam::280112444307:user/maoarias",
                "AttachedManagedPolicies": [
                    {
                        "PolicyArn": "arn:aws:iam::aws:policy/AmazonS3FullAccess",
                        "PolicyName": "AmazonS3FullAccess"
                    },
                    {
                        "PolicyArn": "arn:aws:iam::280112444307:policy/Full-Admin",
                        "PolicyName": "Full-Admin"
                    }
                ],
                "CreateDate": "2021-12-19 18:43:07+00:00",
                "GroupList": [
                    "Full-accessS3",
                    "TFMRead",
                    "Tfmaudit"
                ],
                "Path": "/",
                "Tags": [],
                "UserId": "AIDAUCOAAWOJQBKPMWCSE",
                "UserName": "maoarias"
            }
        },
        {
            "User": {
                "Arn": "arn:aws:iam::280112444307:user/osp",
                "AttachedManagedPolicies": [
                    {
                        "PolicyArn": "arn:aws:iam::aws:policy/AmazonS3FullAccess",
                        "PolicyName": "AmazonS3FullAccess"
                    },
                    {
                        "PolicyArn": "arn:aws:iam::aws:policy/AdministratorAccess",
                        "PolicyName": "AdministratorAccess"
                    },
                    {
                        "PolicyArn": "arn:aws:iam::280112444307:policy/Full-Admin",
                        "PolicyName": "Full-Admin"
                    }
                ],
                "CreateDate": "2021-11-25 09:30:13+00:00",
                "GroupList": [
                    "Full-accessS3"
                ],
                "Path": "/",
                "Tags": [],
                "UserId": "AIDAUCOAAWOJSM23V3XL5",
                "UserName": "osp"
            }
        }
    ]
}